setup.cfg
setup.py
ansible_toolset/__init__.py
ansible_toolset/consts.py
ansible_toolset/models.py
ansible_toolset/utils.py
ansible_toolset/vault.py
ansible_toolset.egg-info/PKG-INFO
ansible_toolset.egg-info/SOURCES.txt
ansible_toolset.egg-info/dependency_links.txt
ansible_toolset.egg-info/requires.txt
ansible_toolset.egg-info/top_level.txt
ansible_toolset/ansible/__init__.py
ansible_toolset/ansible/auto.py
ansible_toolset/ansible/base.py
ansible_toolset/ansible/version20.py
ansible_toolset/ansible/version22.py
bin/ats-vault