Metadata-Version: 1.0
Name: ansible-toolset
Version: 0.7.0
Summary: Useful Ansible toolset
Home-page: https://github.com/krzysztof-magosa/ansible-toolset
Author: Krzysztof Magosa
Author-email: krzysztof@magosa.pl
License: GPLv3
Platform: UNKNOWN
